{
  "collectionName": "components_cta_ctas",
  "info": {
    "displayName": "CTA"
  },
  "options": {},
  "attributes": {
    "Label": {
      "type": "string"
    },
    "Theme": {
      "type": "enumeration",
      "enum": [
        "primary",
        "secondary",
        "outline",
        "anchor_link"
      ],
      "default": "primary"
    },
    "Custom_Link": {
      "type": "string"
    },
    "Target": {
      "type": "enumeration",
      "enum": [
        "none",
        "_blank"
      ]
    }
  }
}
